main.py
setup.py
IRASim.egg-info/PKG-INFO
IRASim.egg-info/SOURCES.txt
IRASim.egg-info/dependency_links.txt
IRASim.egg-info/requires.txt
IRASim.egg-info/top_level.txt